ta_envy/__init__.py
ta_envy-0.1.2.dist-info/METADATA
ta_envy-0.1.2.dist-info/WHEEL
ta_envy-0.1.2.dist-info/licenses/LICENSE
ta_envy-0.1.2.dist-info/RECORD
