Metadata-Version: 2.4
Name: ta-envy
Version: 0.1.2
Summary: A minimal environment variable loader with validation and typing
Author: Thiago Ananias
License: MIT
License-File: LICENSE
Keywords: configuration,dotenv,env,settings
Classifier: License :: OSI Approved :: MIT License
Classifier: Programming Language :: Python :: 3
Requires-Python: >=3.8
Requires-Dist: build>=1.2.2.post1
